maze_utils/__init__.py
maze_utils/custom_logging.py
maze_utils/mazes/__init__.py
maze_utils/mazes/base.py
maze_utils/mazes/depth_first_maze.py
maze_utils/mazes/kruskal_maze.py
maze_utils/mazes/prim_maze.py
maze_utils/mazes/random_filled_maze.py
maze_utils/mazes/recursive_division_maze.py
maze_utils/mazes/wilson_maze.py
maze_utils/solvers/__init__.py
maze_utils/solvers/a_star_solver.py
maze_utils/solvers/base.py
maze_utils/solvers/bidirectional_solver.py
maze_utils/solvers/dijkstra_solver.py
tests/__init__.py
tests/test_mazes.py
tests/test_solvers.py
maze_utils-1.1.1.dist-info/LICENSE
maze_utils-1.1.1.dist-info/METADATA
maze_utils-1.1.1.dist-info/WHEEL
maze_utils-1.1.1.dist-info/top_level.txt
maze_utils-1.1.1.dist-info/RECORD
