Metadata-Version: 2.1
Name: maze-utils
Version: 1.1.1
Summary: A maze generator and solution generator
Author: Robert C. Powel
Author-email: robertcpowel@gmail.com
License: MIT
License-File: LICENSE
Requires-Dist: numpy
Requires-Dist: scipy
Provides-Extra: testing
Requires-Dist: pytest ; extra == 'testing'
Requires-Dist: black ; extra == 'testing'
Requires-Dist: flake8 ; extra == 'testing'
